yaapp/__init__.py
yaapp/app.py
yaapp/async_compat.py
yaapp/cli.py
yaapp/client.py
yaapp/config.py
yaapp/context_tree.py
yaapp/core.py
yaapp/execution_strategy.py
yaapp/reflection.py
yaapp/reflection_utils.py
yaapp/result.py
yaapp/exposers/__init__.py
yaapp/exposers/base.py
yaapp/exposers/class_exposer.py
yaapp/exposers/custom.py
yaapp/exposers/function.py
yaapp/exposers/object.py
yaapp/plugins/__init__.py
yaapp/plugins/app_proxy/__init__.py
yaapp/plugins/app_proxy/plugin.py
yaapp/plugins/routing/__init__.py
yaapp/plugins/routing/plugin.py
yaapp/plugins/session_handler/__init__.py
yaapp/plugins/session_handler/plugin.py
yaapp/plugins/state/__init__.py
yaapp/plugins/state/approval.py
yaapp/plugins/state/base.py
yaapp/plugins/state/issue.py
yaapp/plugins/state/order.py
yaapp/plugins/storage/__init__.py
yaapp/plugins/storage/plugin.py
yaapp/plugins/storage/git/__init__.py
yaapp/plugins/storage/git/backend.py
yaapp/plugins/subprocess_manager/__init__.py
yaapp/plugins/subprocess_manager/plugin.py
yaapp/runners/__init__.py
yaapp/runners/base.py
yaapp/runners/click_runner.py
yaapp/runners/fastapi_runner.py
yaapp/runners/interactive_base.py
yaapp/runners/prompt_runner.py
yaapp/runners/rich_runner.py
yaapp/runners/typer_runner.py
yaapp-0.1.1.dist-info/METADATA
yaapp-0.1.1.dist-info/WHEEL
yaapp-0.1.1.dist-info/entry_points.txt
yaapp-0.1.1.dist-info/top_level.txt
yaapp-0.1.1.dist-info/RECORD
